{"stats":{"minecraft:mined":{"minecraft:iron_ore":10,"minecraft:wheat":23,"minecraft:dandelion":17,"minecraft:cornflower":8,"minecraft:short_grass":6,"minecraft:coal_ore":119,"minecraft:grass_block":3,"minecraft:potatoes":1,"minecraft:oak_log":23,"minecraft:poppy":1,"minecraft:dripstone_block":1,"minecraft:dirt":2,"minecraft:cobblestone":3,"minecraft:tall_grass":1,"minecraft:stone":113,"minecraft:oxeye_daisy":1,"minecraft:oak_leaves":3},"minecraft:custom":{"minecraft:time_since_rest":35079,"minecraft:interact_with_furnace":1,"minecraft:sprint_one_cm":117991,"minecraft:damage_taken":698,"minecraft:walk_one_cm":145672,"minecraft:mob_kills":2,"minecraft:drop":1,"minecraft:damage_dealt":380,"minecraft:swim_one_cm":1962,"minecraft:interact_with_crafting_table":3,"minecraft:fly_one_cm":86101,"minecraft:open_chest":17,"minecraft:crouch_one_cm":8724,"minecraft:play_time":47979,"minecraft:sneak_time":3314,"minecraft:walk_under_water_one_cm":372,"minecraft:jump":775,"minecraft:time_since_death":47979,"minecraft:walk_on_water_one_cm":1132,"minecraft:sleep_in_bed":1,"minecraft:total_world_time":47979,"minecraft:fall_one_cm":16124},"minecraft:dropped":{"minecraft:diamond_sword":1},"minecraft:used":{"minecraft:wooden_axe":23,"minecraft:bread":5,"minecraft:iron_pickaxe":252,"minecraft:diamond_sword":6,"minecraft:wooden_sword":15,"minecraft:dirt":3,"minecraft:cobblestone":83,"minecraft:crafting_table":1,"minecraft:oak_sapling":2,"minecraft:carrot":12,"minecraft:yellow_bed":1,"minecraft:egg":1},"minecraft:broken":{"minecraft:iron_pickaxe":1},"minecraft:crafted":{"minecraft:wooden_sword":1,"minecraft:oak_planks":16,"minecraft:crafting_table":2,"minecraft:stick":4,"minecraft:wooden_axe":1,"minecraft:bread":5},"minecraft:picked_up":{"minecraft:raw_iron":11,"minecraft:stick":4,"minecraft:wheat":17,"minecraft:diamond_sword":1,"minecraft:dandelion":16,"minecraft:dripstone_block":1,"minecraft:potato":1,"minecraft:oak_log":24,"minecraft:carrot":16,"minecraft:cornflower":7,"minecraft:dirt":4,"minecraft:arrow":2,"minecraft:rotten_flesh":3,"minecraft:wheat_seeds":53,"minecraft:poppy":1,"minecraft:iron_pickaxe":1,"minecraft:oak_sapling":2,"minecraft:coal":119,"minecraft:egg":1,"minecraft:cobblestone":115,"minecraft:oxeye_daisy":1},"minecraft:killed":{"minecraft:zombie_villager":1}},"DataVersion":3953}