{"stats":{"minecraft:mined":{"minecraft:iron_ore":10,"minecraft:wheat":23,"minecraft:dandelion":17,"minecraft:cornflower":8,"minecraft:short_grass":4,"minecraft:coal_ore":119,"minecraft:grass_block":3,"minecraft:potatoes":1,"minecraft:oak_log":23,"minecraft:poppy":1,"minecraft:dripstone_block":1,"minecraft:dirt":2,"minecraft:cobblestone":3,"minecraft:tall_grass":1,"minecraft:stone":113,"minecraft:oxeye_daisy":1,"minecraft:oak_leaves":3},"minecraft:custom":{"minecraft:time_since_rest":23079,"minecraft:sprint_one_cm":75090,"minecraft:damage_taken":562,"minecraft:walk_one_cm":113125,"minecraft:damage_dealt":18,"minecraft:swim_one_cm":1544,"minecraft:interact_with_crafting_table":3,"minecraft:fly_one_cm":56069,"minecraft:open_chest":11,"minecraft:crouch_one_cm":5631,"minecraft:play_time":35979,"minecraft:sneak_time":2439,"minecraft:walk_under_water_one_cm":372,"minecraft:jump":595,"minecraft:time_since_death":35979,"minecraft:walk_on_water_one_cm":1132,"minecraft:sleep_in_bed":1,"minecraft:total_world_time":35979,"minecraft:fall_one_cm":13392},"minecraft:used":{"minecraft:wooden_axe":23,"minecraft:bread":5,"minecraft:iron_pickaxe":250,"minecraft:dirt":3,"minecraft:cobblestone":76,"minecraft:crafting_table":1,"minecraft:oak_sapling":2,"minecraft:carrot":10,"minecraft:egg":1},"minecraft:broken":{"minecraft:iron_pickaxe":1},"minecraft:crafted":{"minecraft:wooden_sword":1,"minecraft:oak_planks":16,"minecraft:crafting_table":2,"minecraft:stick":4,"minecraft:wooden_axe":1,"minecraft:bread":5},"minecraft:picked_up":{"minecraft:raw_iron":11,"minecraft:stick":4,"minecraft:wheat":17,"minecraft:dandelion":16,"minecraft:dripstone_block":1,"minecraft:potato":1,"minecraft:oak_log":24,"minecraft:carrot":16,"minecraft:cornflower":7,"minecraft:dirt":4,"minecraft:wheat_seeds":53,"minecraft:poppy":1,"minecraft:iron_pickaxe":1,"minecraft:oak_sapling":2,"minecraft:coal":119,"minecraft:egg":1,"minecraft:cobblestone":115,"minecraft:oxeye_daisy":1}},"DataVersion":3953}